[{"model": "auth.user", "fields": {"password": "pbkdf2_sha256$1200000$peaiI7dJUAiLCbbX4V2T4Y$RnqI4Shd8FOcEqz1aeSTHjDwIM7v3zRuK1FlfPRxz60=", "last_login": "2026-06-05T15:42:48.123Z", "is_superuser": true, "username": "admin", "first_name": "", "last_name": "", "email": "admin@direccion.gob.ve", "is_staff": true, "is_active": true, "date_joined": "2026-06-02T17:50:19.771Z", "groups": [], "user_permissions": []}}, {"model": "auth.user", "fields": {"password": "pbkdf2_sha256$1200000$F4XUspO57XDdhOdoi1ZNtV$EZ1HLBtvk8v8Yb7rUdZ9plGHjY0JWkVDKhHsIpR4BRk=", "last_login": "2026-06-04T21:13:15.496Z", "is_superuser": false, "username": "analista", "first_name": "Carlos", "last_name": "Analista", "email": "analista@test.com", "is_staff": false, "is_active": true, "date_joined": "2026-06-03T17:01:58.724Z", "groups": [], "user_permissions": []}}, {"model": "auth.user", "fields": {"password": "pbkdf2_sha256$1200000$Xoo3zpPT1OOR6BQkPl4rlA$K7utMlojmTsRizlRGNkQsMq5U9BwxwadwMHlt2EpziQ=", "last_login": null, "is_superuser": false, "username": "administrativo", "first_name": "Maria", "last_name": "Adminis", "email": "adminis@test.com", "is_staff": false, "is_active": true, "date_joined": "2026-06-03T17:01:59.173Z", "groups": [], "user_permissions": []}}, {"model": "auth.user", "fields": {"password": "pbkdf2_sha256$1200000$ewptC90th8WDVyRhOv2ltt$mhTuxnMjihQAnPgJhPxPSEQDXh/hWKN5xIB6kKGfYV8=", "last_login": "2026-06-03T19:19:33.282Z", "is_superuser": false, "username": "angelina", "first_name": "", "last_name": "", "email": "capangelina@gmail.com", "is_staff": false, "is_active": true, "date_joined": "2026-06-03T18:04:30.506Z", "groups": [], "user_permissions": []}}, {"model": "auth.user", "fields": {"password": "pbkdf2_sha256$1200000$J1INnDFnFECCenP6jvP32v$P5R9eFf3GrBViFdNxtPtU6FwwZ7AlYiZhH3aUbdvrlo=", "last_login": "2026-06-03T22:43:10.086Z", "is_superuser": false, "username": "carlosmasacre", "first_name": "", "last_name": "", "email": "capangelina@gmail.com", "is_staff": false, "is_active": true, "date_joined": "2026-06-03T22:40:39.769Z", "groups": [], "user_permissions": []}}, {"model": "auth.user", "fields": {"password": "pbkdf2_sha256$1200000$ZRIdhdf5JdeH49aOT9hQGC$ZUmloYx4u/BWAxnj6/3lG51eFxg3XMHkPsegZaZNoeA=", "last_login": "2026-06-04T16:28:43.369Z", "is_superuser": false, "username": "tirsomota", "first_name": "Tirso", "last_name": "Mota", "email": "", "is_staff": false, "is_active": true, "date_joined": "2026-06-04T16:25:46.602Z", "groups": [], "user_permissions": []}}, {"model": "auth.user", "fields": {"password": "pbkdf2_sha256$1200000$c75dqp3frISwuamXBPqlZp$FwAggVKZAEYRzuDTuQE94XZjiewt9EX+BpwMSrXew1c=", "last_login": "2026-06-04T20:33:17.668Z", "is_superuser": false, "username": "diag_admin", "first_name": "Admin", "last_name": "", "email": "d@a.com", "is_staff": false, "is_active": true, "date_joined": "2026-06-04T20:33:17.218Z", "groups": [], "user_permissions": []}}, {"model": "auth.user", "fields": {"password": "pbkdf2_sha256$1200000$pDqyOH2ix4BtVL5TjVrWYs$Mtknh+SEOARo4rkSybppCVkn2DGp+EwC4Be4BfE/G3U=", "last_login": "2026-06-04T20:33:36.481Z", "is_superuser": false, "username": "diag_admin2", "first_name": "Admin", "last_name": "Test", "email": "d2@a.com", "is_staff": false, "is_active": true, "date_joined": "2026-06-04T20:33:35.377Z", "groups": [], "user_permissions": []}}, {"model": "auth.user", "fields": {"password": "pbkdf2_sha256$1200000$bQQ55zj0ezzsqe1VSyO11r$PdycdiMlquPVBZlOsNilRHjVFsurI++QlYU/HrCM2AE=", "last_login": "2026-06-04T20:34:01.054Z", "is_superuser": false, "username": "diag_admin3", "first_name": "Admin", "last_name": "Test", "email": "d3@a.com", "is_staff": false, "is_active": true, "date_joined": "2026-06-04T20:34:00.507Z", "groups": [], "user_permissions": []}}, {"model": "auth.user", "fields": {"password": "pbkdf2_sha256$1200000$Hov71P3Xo6JYQITuKleWPO$0GIlB5Rp77mvfzOqBQONTQoR5mLaVqYpa3c4tpIai+k=", "last_login": "2026-06-04T20:34:17.651Z", "is_superuser": true, "username": "diag_super", "first_name": "", "last_name": "", "email": "ds@a.com", "is_staff": true, "is_active": true, "date_joined": "2026-06-04T20:34:17.102Z", "groups": [], "user_permissions": []}}, {"model": "thumbnail.kvstore", "pk": "sorl-thumbnail||image||6616c3d30db54931ef065093e35067a4", "fields": {"value": "{\"name\": \"personal/documentos/V-12345678/Garzon.PNG\", \"storage\": \"django.core.files.storage.filesystem.FileSystemStorage\", \"size\": [205, 243]}"}}, {"model": "thumbnail.kvstore", "pk": "sorl-thumbnail||image||78d2b13499b0110eacfad32922d942a9", "fields": {"value": "{\"name\": \"cache/08/61/0861ee482476c1e405938defadb508fb.webp\", \"storage\": \"django.core.files.storage.filesystem.FileSystemStorage\", \"size\": [400, 400]}"}}, {"model": "thumbnail.kvstore", "pk": "sorl-thumbnail||image||79e45320fca4b13f3266a104f51d7ffb", "fields": {"value": "{\"name\": \"cache/18/a5/18a5fe8bb430fb7549c2fd36c9d27924.webp\", \"storage\": \"django.core.files.storage.filesystem.FileSystemStorage\", \"size\": [400, 400]}"}}, {"model": "thumbnail.kvstore", "pk": "sorl-thumbnail||image||ac5e5ca206ce677ac0425ff48f79d569", "fields": {"value": "{\"name\": \"cache/a5/36/a53688424056e58c030882088962bd08.webp\", \"storage\": \"django.core.files.storage.filesystem.FileSystemStorage\", \"size\": [400, 400]}"}}, {"model": "thumbnail.kvstore", "pk": "sorl-thumbnail||image||c5cf16040d1ec04f6427ef6dbbd23c55", "fields": {"value": "{\"name\": \"personal/documentos/V-12345678/echarri.png\", \"storage\": \"django.core.files.storage.filesystem.FileSystemStorage\", \"size\": [206, 262]}"}}, {"model": "thumbnail.kvstore", "pk": "sorl-thumbnail||image||f388c2403172ebe7a9e47e622a1a0e62", "fields": {"value": "{\"name\": \"personal/documentos/V-12345678/apitz_padre.PNG\", \"storage\": \"django.core.files.storage.filesystem.FileSystemStorage\", \"size\": [175, 226]}"}}, {"model": "thumbnail.kvstore", "pk": "sorl-thumbnail||thumbnails||6616c3d30db54931ef065093e35067a4", "fields": {"value": "[\"ac5e5ca206ce677ac0425ff48f79d569\"]"}}, {"model": "thumbnail.kvstore", "pk": "sorl-thumbnail||thumbnails||c5cf16040d1ec04f6427ef6dbbd23c55", "fields": {"value": "[\"78d2b13499b0110eacfad32922d942a9\"]"}}, {"model": "thumbnail.kvstore", "pk": "sorl-thumbnail||thumbnails||f388c2403172ebe7a9e47e622a1a0e62", "fields": {"value": "[\"79e45320fca4b13f3266a104f51d7ffb\"]"}}, {"model": "direccion.userprofile", "pk": 1, "fields": {"user": ["admin"], "rol": "ADMINISTRADOR", "telefono": null}}, {"model": "direccion.userprofile", "pk": 2, "fields": {"user": ["analista"], "rol": "ANALISTA", "telefono": null}}, {"model": "direccion.userprofile", "pk": 3, "fields": {"user": ["administrativo"], "rol": "ADMINISTRATIVO", "telefono": null}}, {"model": "direccion.userprofile", "pk": 4, "fields": {"user": ["angelina"], "rol": "ADMINISTRATIVO", "telefono": null}}, {"model": "direccion.userprofile", "pk": 5, "fields": {"user": ["carlosmasacre"], "rol": "ADMINISTRADOR", "telefono": null}}, {"model": "direccion.userprofile", "pk": 6, "fields": {"user": ["tirsomota"], "rol": "ADMINISTRADOR", "telefono": null}}, {"model": "direccion.userprofile", "pk": 7, "fields": {"user": ["diag_admin"], "rol": "ADMINISTRADOR", "telefono": null}}, {"model": "direccion.userprofile", "pk": 8, "fields": {"user": ["diag_admin2"], "rol": "ADMINISTRADOR", "telefono": null}}, {"model": "direccion.userprofile", "pk": 9, "fields": {"user": ["diag_admin3"], "rol": "ADMINISTRADOR", "telefono": null}}, {"model": "direccion.userprofile", "pk": 10, "fields": {"user": ["diag_super"], "rol": "ADMINISTRADOR", "telefono": null}}, {"model": "direccion.personal", "pk": 2, "fields": {"foto": "personal/fotos/V-19956015_PAREDES_TORREALBA_MARIA_DE_LOS_ANGELES.jpg", "apellidos": "PAREDES TORREALBA", "nombres": "MARIA DE LOS ANGELES", "cedula": "V-19956015", "rango": "", "telefonos": "0424-553-8460", "fecha_nacimiento": null, "fecha_creacion": "2026-06-04T20:52:19.397Z", "fecha_actualizacion": "2026-06-04T20:52:26.217Z", "activo": true}}, {"model": "direccion.personal", "pk": 3, "fields": {"foto": "personal/fotos/V-16043808_GARCIA_BETSIS_DEL_CARMEN.jpg", "apellidos": "GARCIA", "nombres": "BETSIS DEL CARMEN", "cedula": "V-16043808", "rango": "", "telefonos": "0414-1633132", "fecha_nacimiento": "2026-03-05", "fecha_creacion": "2026-06-04T20:54:01.700Z", "fecha_actualizacion": "2026-06-04T20:54:15.748Z", "activo": true}}, {"model": "direccion.documentopersonal", "pk": 7, "fields": {"personal": 2, "archivo": "personal/documentos/V-19956015/Ley-Organica-de-Seguridad-de-la-NAci├▓n.pdf", "tipo": "PDF", "descripcion": null, "fecha_subida": "2026-06-04T20:52:43.637Z"}}, {"model": "direccion.investigado", "pk": 1, "fields": {"caso": null, "foto": "investigados/fotos/V-13338296_Rubiano_Colmenares_Jos├®_Alejandro.png", "apellidos": "Rubiano Colmenares", "nombres": "Jos├® Alejandro", "entrada_investigacion": "El 14/02/2016, a partir del an├Īlisis de la informaci├│n bancaria, se identific├│ un v├Łnculo directo entre el titular de la cuenta Gabriel Requena y Rubiano Colmenares, evidenciado por una transacci├│n de alto valor que sugiere la contrataci├│n de servicios especializados asociados a la movilizaci├│n de recursos o a la log├Łstica de eventos.", "cedula": "V-13338296", "rif": null, "partida_nacimiento": "11121978", "fecha_creacion": "2026-06-04T20:55:45.572Z", "fecha_actualizacion": "2026-06-04T20:55:45.572Z", "activo": true}}, {"model": "direccion.documentodireccion", "pk": 3, "fields": {"archivo": "direccion/documentos/LEY_ORG├üNICA_DE_SEGURIDAD_DE_LA_NACI├ōN.pdf", "tipo": "PDF", "categoria": "LEYES", "descripcion": null, "fecha_subida": "2026-06-04T16:13:15.761Z"}}, {"model": "direccion.documentodireccion", "pk": 4, "fields": {"archivo": "direccion/documentos/LEY_ORG├üNICA_CONTRA_LA_DELINCUENCIA_ORGANIZADA_.pdf", "tipo": "PDF", "categoria": "LEYES", "descripcion": null, "fecha_subida": "2026-06-04T16:13:27.024Z"}}, {"model": "direccion.auditlog", "pk": 1, "fields": {"usuario": ["admin"], "username": "admin", "accion": "CREAR", "modelo": "Personal", "objeto_id": 1, "objeto_repr": "Perez Suarez, Juana Maria - V-12345678", "detalle": "C├®dula: V-12345678", "direccion_ip": "127.0.0.1", "fecha": "2026-06-03T13:21:53.259Z"}}, {"model": "direccion.auditlog", "pk": 2, "fields": {"usuario": ["admin"], "username": "admin", "accion": "ACTUALIZAR", "modelo": "Personal", "objeto_id": 1, "objeto_repr": "Perez Suarez, Juana Maria - V-12345678", "detalle": "C├®dula: V-12345678", "direccion_ip": "127.0.0.1", "fecha": "2026-06-03T13:22:41.132Z"}}, {"model": "direccion.auditlog", "pk": 3, "fields": {"usuario": ["admin"], "username": "admin", "accion": "CREAR", "modelo": "DocumentoPersonal", "objeto_id": 1, "objeto_repr": "Perez Suarez, Juana Maria - V-12345678 - Informe_Patrimonial.pdf", "detalle": "Personal: Perez Suarez, Juana Maria - V-12345678", "direccion_ip": "127.0.0.1", "fecha": "2026-06-03T13:46:42.939Z"}}, {"model": "direccion.auditlog", "pk": 4, "fields": {"usuario": ["admin"], "username": "admin", "accion": "EXPORTAR", "modelo": "Personal", "objeto_id": null, "objeto_repr": "Exportaci├│n PDF", "detalle": "1 registros", "direccion_ip": "127.0.0.1", "fecha": "2026-06-03T16:15:45.178Z"}}, {"model": "direccion.auditlog", "pk": 5, "fields": {"usuario": ["admin"], "username": "admin", "accion": "EXPORTAR", "modelo": "Personal", "objeto_id": null, "objeto_repr": "Exportaci├│n Excel", "detalle": "1 registros", "direccion_ip": "127.0.0.1", "fecha": "2026-06-03T16:16:00.273Z"}}, {"model": "direccion.auditlog", "pk": 6, "fields": {"usuario": ["admin"], "username": "admin", "accion": "ACTUALIZAR", "modelo": "Personal", "objeto_id": 1, "objeto_repr": "Perez Suarez, Juana Maria - V-12345678", "detalle": "C├®dula: V-12345678", "direccion_ip": "127.0.0.1", "fecha": "2026-06-03T16:16:24.010Z"}}, {"model": "direccion.auditlog", "pk": 7, "fields": {"usuario": ["admin"], "username": "admin", "accion": "CREAR", "modelo": "DocumentoPersonal", "objeto_id": 2, "objeto_repr": "Perez Suarez, Juana Maria - V-12345678 - echarri.png", "detalle": "Personal: Perez Suarez, Juana Maria - V-12345678", "direccion_ip": "127.0.0.1", "fecha": "2026-06-03T16:16:47.057Z"}}, {"model": "direccion.auditlog", "pk": 8, "fields": {"usuario": ["admin"], "username": "admin", "accion": "BACKUP", "modelo": "Sistema", "objeto_id": null, "objeto_repr": "Descarga de respaldo", "detalle": "respaldo_20260603_121854.zip - 4 archivos", "direccion_ip": "127.0.0.1", "fecha": "2026-06-03T16:18:54.434Z"}}, {"model": "direccion.auditlog", "pk": 9, "fields": {"usuario": ["admin"], "username": "admin", "accion": "ELIMINAR", "modelo": "DocumentoPersonal", "objeto_id": 1, "objeto_repr": "Perez Suarez, Juana Maria - V-12345678 - Informe_Patrimonial.pdf", "detalle": "Personal: Perez Suarez, Juana Maria - V-12345678", "direccion_ip": "172.10.2.13", "fecha": "2026-06-03T17:28:39.759Z"}}, {"model": "direccion.auditlog", "pk": 10, "fields": {"usuario": ["admin"], "username": "admin", "accion": "ELIMINAR", "modelo": "DocumentoPersonal", "objeto_id": 2, "objeto_repr": "Perez Suarez, Juana Maria - V-12345678 - echarri.png", "detalle": "Personal: Perez Suarez, Juana Maria - V-12345678", "direccion_ip": "172.10.2.13", "fecha": "2026-06-03T17:28:43.223Z"}}, {"model": "direccion.auditlog", "pk": 11, "fields": {"usuario": ["admin"], "username": "admin", "accion": "CREAR", "modelo": "DocumentoPersonal", "objeto_id": 3, "objeto_repr": "Perez Suarez, Juana Maria - V-12345678 - Garzon.PNG", "detalle": "Personal: Perez Suarez, Juana Maria - V-12345678", "direccion_ip": "172.10.2.13", "fecha": "2026-06-03T17:28:53.570Z"}}, {"model": "direccion.auditlog", "pk": 12, "fields": {"usuario": ["admin"], "username": "admin", "accion": "CREAR", "modelo": "DocumentoPersonal", "objeto_id": 4, "objeto_repr": "Perez Suarez, Juana Maria - V-12345678 - apitz_padre.PNG", "detalle": "Personal: Perez Suarez, Juana Maria - V-12345678", "direccion_ip": "172.10.2.13", "fecha": "2026-06-03T17:28:57.748Z"}}, {"model": "direccion.auditlog", "pk": 13, "fields": {"usuario": ["admin"], "username": "admin", "accion": "CREAR", "modelo": "DocumentoPersonal", "objeto_id": 5, "objeto_repr": "Perez Suarez, Juana Maria - V-12345678 - I.I.F_Miguel_Angel_Suarez_CIN5.docx", "detalle": "Personal: Perez Suarez, Juana Maria - V-12345678", "direccion_ip": "172.10.2.13", "fecha": "2026-06-03T17:29:02.958Z"}}, {"model": "direccion.auditlog", "pk": 14, "fields": {"usuario": ["admin"], "username": "admin", "accion": "ELIMINAR", "modelo": "DocumentoPersonal", "objeto_id": 5, "objeto_repr": "Perez Suarez, Juana Maria - V-12345678 - I.I.F_Miguel_Angel_Suarez_CIN5.docx", "detalle": "Personal: Perez Suarez, Juana Maria - V-12345678", "direccion_ip": "172.10.2.13", "fecha": "2026-06-03T17:29:09.247Z"}}, {"model": "direccion.auditlog", "pk": 15, "fields": {"usuario": ["admin"], "username": "admin", "accion": "ELIMINAR", "modelo": "DocumentoPersonal", "objeto_id": 3, "objeto_repr": "Perez Suarez, Juana Maria - V-12345678 - Garzon.PNG", "detalle": "Personal: Perez Suarez, Juana Maria - V-12345678", "direccion_ip": "172.10.2.13", "fecha": "2026-06-03T17:29:12.292Z"}}, {"model": "direccion.auditlog", "pk": 16, "fields": {"usuario": ["admin"], "username": "admin", "accion": "ELIMINAR", "modelo": "DocumentoPersonal", "objeto_id": 4, "objeto_repr": "Perez Suarez, Juana Maria - V-12345678 - apitz_padre.PNG", "detalle": "Personal: Perez Suarez, Juana Maria - V-12345678", "direccion_ip": "172.10.2.13", "fecha": "2026-06-03T17:29:14.446Z"}}, {"model": "direccion.auditlog", "pk": 17, "fields": {"usuario": ["admin"], "username": "admin", "accion": "CREAR", "modelo": "DocumentoPersonal", "objeto_id": 6, "objeto_repr": "Perez Suarez, Juana Maria - V-12345678 - img20260505_08535066.pdf", "detalle": "Personal: Perez Suarez, Juana Maria - V-12345678", "direccion_ip": "172.10.2.13", "fecha": "2026-06-03T17:54:12.555Z"}}, {"model": "direccion.auditlog", "pk": 18, "fields": {"usuario": ["admin"], "username": "admin", "accion": "ELIMINAR", "modelo": "DocumentoPersonal", "objeto_id": 6, "objeto_repr": "Perez Suarez, Juana Maria - V-12345678 - img20260505_08535066.pdf", "detalle": "Personal: Perez Suarez, Juana Maria - V-12345678", "direccion_ip": "172.10.2.13", "fecha": "2026-06-03T17:54:22.184Z"}}, {"model": "direccion.auditlog", "pk": 19, "fields": {"usuario": ["admin"], "username": "admin", "accion": "CREAR", "modelo": "Usuario", "objeto_id": 4, "objeto_repr": "angelina", "detalle": "Rol: ADMINISTRATIVO", "direccion_ip": "172.10.2.13", "fecha": "2026-06-03T18:04:31.231Z"}}, {"model": "direccion.auditlog", "pk": 20, "fields": {"usuario": ["admin"], "username": "admin", "accion": "EXPORTAR", "modelo": "Personal", "objeto_id": null, "objeto_repr": "Exportaci├│n PDF", "detalle": "1 registros", "direccion_ip": "172.10.2.32", "fecha": "2026-06-03T18:07:58.152Z"}}, {"model": "direccion.auditlog", "pk": 21, "fields": {"usuario": ["admin"], "username": "admin", "accion": "TOGGLE", "modelo": "Usuario", "objeto_id": 4, "objeto_repr": "angelina", "detalle": "Cuenta desactivada", "direccion_ip": "172.10.2.13", "fecha": "2026-06-03T18:24:52.520Z"}}, {"model": "direccion.auditlog", "pk": 22, "fields": {"usuario": ["admin"], "username": "admin", "accion": "TOGGLE", "modelo": "Usuario", "objeto_id": 4, "objeto_repr": "angelina", "detalle": "Cuenta activada", "direccion_ip": "172.10.2.13", "fecha": "2026-06-03T18:35:14.486Z"}}, {"model": "direccion.auditlog", "pk": 23, "fields": {"usuario": ["admin"], "username": "admin", "accion": "CREAR", "modelo": "DocumentoDireccion", "objeto_id": 1, "objeto_repr": "Sin descripci├ā┬│n - Sello.pdf", "detalle": "Documento Direccion", "direccion_ip": "172.10.2.13", "fecha": "2026-06-03T21:01:17.452Z"}}, {"model": "direccion.auditlog", "pk": 24, "fields": {"usuario": ["admin"], "username": "admin", "accion": "ELIMINAR", "modelo": "DocumentoDireccion", "objeto_id": 1, "objeto_repr": "Sin descripci├ā┬│n - Sello.pdf", "detalle": "Documento Direccion", "direccion_ip": "172.10.2.13", "fecha": "2026-06-03T21:01:30.332Z"}}, {"model": "direccion.auditlog", "pk": 25, "fields": {"usuario": ["admin"], "username": "admin", "accion": "CREAR", "modelo": "Usuario", "objeto_id": 5, "objeto_repr": "carlosmasacre", "detalle": "Rol: ADMINISTRADOR", "direccion_ip": "172.10.2.13", "fecha": "2026-06-03T22:40:40.511Z"}}, {"model": "direccion.auditlog", "pk": 26, "fields": {"usuario": ["carlosmasacre"], "username": "carlosmasacre", "accion": "CREAR", "modelo": "DocumentoDireccion", "objeto_id": 2, "objeto_repr": "Sin descripci├ā┬│n - INFORME_DIARIO_03-6-26-docx.pdf", "detalle": "Documento Direccion", "direccion_ip": "172.10.2.7", "fecha": "2026-06-03T22:43:38.007Z"}}, {"model": "direccion.auditlog", "pk": 27, "fields": {"usuario": ["carlosmasacre"], "username": "carlosmasacre", "accion": "ELIMINAR", "modelo": "DocumentoDireccion", "objeto_id": 2, "objeto_repr": "Sin descripci├ā┬│n - INFORME_DIARIO_03-6-26-docx.pdf", "detalle": "Documento Direccion", "direccion_ip": "172.10.2.7", "fecha": "2026-06-03T22:43:55.318Z"}}, {"model": "direccion.auditlog", "pk": 28, "fields": {"usuario": ["carlosmasacre"], "username": "carlosmasacre", "accion": "EXPORTAR", "modelo": "Personal", "objeto_id": null, "objeto_repr": "Exportaci├│n PDF", "detalle": "1 registros", "direccion_ip": "172.10.2.7", "fecha": "2026-06-03T22:44:16.744Z"}}, {"model": "direccion.auditlog", "pk": 29, "fields": {"usuario": ["admin"], "username": "admin", "accion": "CREAR", "modelo": "DocumentoDireccion", "objeto_id": 3, "objeto_repr": "Sin descripci├│n - LEY_ORG├üNICA_DE_SEGURIDAD_DE_LA_NACI├ōN.pdf", "detalle": "Documento Direccion", "direccion_ip": "127.0.0.1", "fecha": "2026-06-04T16:13:15.769Z"}}, {"model": "direccion.auditlog", "pk": 30, "fields": {"usuario": ["admin"], "username": "admin", "accion": "CREAR", "modelo": "DocumentoDireccion", "objeto_id": 4, "objeto_repr": "Sin descripci├│n - LEY_ORG├üNICA_CONTRA_LA_DELINCUENCIA_ORGANIZADA_.pdf", "detalle": "Documento Direccion", "direccion_ip": "127.0.0.1", "fecha": "2026-06-04T16:13:27.031Z"}}, {"model": "direccion.auditlog", "pk": 31, "fields": {"usuario": ["admin"], "username": "admin", "accion": "CREAR", "modelo": "Usuario", "objeto_id": 6, "objeto_repr": "tirsomota", "detalle": "Rol: ADMINISTRADOR", "direccion_ip": "127.0.0.1", "fecha": "2026-06-04T16:25:47.328Z"}}, {"model": "direccion.auditlog", "pk": 32, "fields": {"usuario": ["admin"], "username": "admin", "accion": "CREAR", "modelo": "DocumentoDireccion", "objeto_id": 5, "objeto_repr": "Sin descripci├│n - LISTADO_PERSONAL.docx", "detalle": "Documento Direccion", "direccion_ip": "127.0.0.1", "fecha": "2026-06-04T16:45:01.018Z"}}, {"model": "direccion.auditlog", "pk": 33, "fields": {"usuario": ["admin"], "username": "admin", "accion": "ELIMINAR", "modelo": "DocumentoDireccion", "objeto_id": 5, "objeto_repr": "Sin descripci├│n - LISTADO_PERSONAL.docx", "detalle": "Documento Direccion", "direccion_ip": "127.0.0.1", "fecha": "2026-06-04T16:45:06.739Z"}}, {"model": "direccion.auditlog", "pk": 34, "fields": {"usuario": ["analista"], "username": "analista", "accion": "EXPORTAR", "modelo": "Personal", "objeto_id": null, "objeto_repr": "Exportaci├│n PDF", "detalle": "1 registros", "direccion_ip": "172.10.2.8", "fecha": "2026-06-04T20:41:06.289Z"}}, {"model": "direccion.auditlog", "pk": 35, "fields": {"usuario": ["admin"], "username": "admin", "accion": "ELIMINAR", "modelo": "Personal", "objeto_id": 1, "objeto_repr": "Perez Suarez, Juana Maria - V-12345678", "detalle": "C├®dula: V-12345678", "direccion_ip": "172.10.2.42", "fecha": "2026-06-04T20:50:19.862Z"}}, {"model": "direccion.auditlog", "pk": 36, "fields": {"usuario": ["admin"], "username": "admin", "accion": "CREAR", "modelo": "Personal", "objeto_id": 2, "objeto_repr": "PAREDES TORREALBA, MARIA DE LOS ANGELES - V-19956015", "detalle": "C├®dula: V-19956015", "direccion_ip": "172.10.2.42", "fecha": "2026-06-04T20:52:19.402Z"}}, {"model": "direccion.auditlog", "pk": 37, "fields": {"usuario": ["admin"], "username": "admin", "accion": "ACTUALIZAR", "modelo": "Personal", "objeto_id": 2, "objeto_repr": "PAREDES TORREALBA, MARIA DE LOS ANGELES - V-19956015", "detalle": "C├®dula: V-19956015", "direccion_ip": "172.10.2.42", "fecha": "2026-06-04T20:52:26.222Z"}}, {"model": "direccion.auditlog", "pk": 38, "fields": {"usuario": ["admin"], "username": "admin", "accion": "CREAR", "modelo": "DocumentoPersonal", "objeto_id": 7, "objeto_repr": "PAREDES TORREALBA, MARIA DE LOS ANGELES - V-19956015 - Ley-Organica-de-Seguridad-de-la-NAci├▓n.pdf", "detalle": "Personal: PAREDES TORREALBA, MARIA DE LOS ANGELES - V-19956015", "direccion_ip": "172.10.2.42", "fecha": "2026-06-04T20:52:43.643Z"}}, {"model": "direccion.auditlog", "pk": 39, "fields": {"usuario": ["admin"], "username": "admin", "accion": "CREAR", "modelo": "Personal", "objeto_id": 3, "objeto_repr": "GARCIA, BETSIS DEL CARMEN - V-16043808", "detalle": "C├®dula: V-16043808", "direccion_ip": "172.10.2.42", "fecha": "2026-06-04T20:54:01.705Z"}}, {"model": "direccion.auditlog", "pk": 40, "fields": {"usuario": ["admin"], "username": "admin", "accion": "ACTUALIZAR", "modelo": "Personal", "objeto_id": 3, "objeto_repr": "GARCIA, BETSIS DEL CARMEN - V-16043808", "detalle": "C├®dula: V-16043808", "direccion_ip": "172.10.2.42", "fecha": "2026-06-04T20:54:15.752Z"}}, {"model": "direccion.auditlog", "pk": 41, "fields": {"usuario": ["admin"], "username": "admin", "accion": "CREAR", "modelo": "Investigado", "objeto_id": 1, "objeto_repr": "Rubiano Colmenares, Jos├® Alejandro - V-13338296", "detalle": "C├®dula: V-13338296", "direccion_ip": "172.10.2.42", "fecha": "2026-06-04T20:55:45.579Z"}}, {"model": "direccion.auditlog", "pk": 42, "fields": {"usuario": ["admin"], "username": "admin", "accion": "CREAR", "modelo": "DocumentoInvestigado", "objeto_id": 1, "objeto_repr": "Rubiano Colmenares, Jos├® Alejandro - V-13338296 - Perfil_Primario_Jos├®_Rubiano.pdf", "detalle": "Investigado: Rubiano Colmenares, Jos├® Alejandro - V-13338296", "direccion_ip": "172.10.2.42", "fecha": "2026-06-04T20:56:02.693Z"}}, {"model": "direccion.auditlog", "pk": 43, "fields": {"usuario": ["admin"], "username": "admin", "accion": "ACTUALIZAR", "modelo": "TicketSoporte", "objeto_id": 1, "objeto_repr": "#1 - Test ticket", "detalle": "Estado: Resuelto", "direccion_ip": "172.10.2.42", "fecha": "2026-06-04T20:56:51.871Z"}}, {"model": "direccion.auditlog", "pk": 44, "fields": {"usuario": ["admin"], "username": "admin", "accion": "ACTUALIZAR", "modelo": "TicketSoporte", "objeto_id": 2, "objeto_repr": "#2 - Test ticket", "detalle": "Estado: Resuelto", "direccion_ip": "172.10.2.42", "fecha": "2026-06-04T20:56:53.691Z"}}, {"model": "direccion.auditlog", "pk": 45, "fields": {"usuario": ["admin"], "username": "admin", "accion": "ACTUALIZAR", "modelo": "TicketSoporte", "objeto_id": 3, "objeto_repr": "#3 - Test", "detalle": "Estado: Resuelto", "direccion_ip": "172.10.2.42", "fecha": "2026-06-04T20:56:54.636Z"}}, {"model": "direccion.auditlog", "pk": 46, "fields": {"usuario": ["admin"], "username": "admin", "accion": "ACTUALIZAR", "modelo": "TicketSoporte", "objeto_id": 1, "objeto_repr": "#1 - Test ticket", "detalle": "Estado: Abierto", "direccion_ip": "172.10.2.42", "fecha": "2026-06-04T20:57:01.395Z"}}, {"model": "direccion.auditlog", "pk": 47, "fields": {"usuario": ["analista"], "username": "analista", "accion": "CREAR", "modelo": "TicketSoporte", "objeto_id": 4, "objeto_repr": "#4 - Prueba", "detalle": "Asunto: Prueba", "direccion_ip": "172.10.2.42", "fecha": "2026-06-04T21:00:22.021Z"}}, {"model": "direccion.auditlog", "pk": 48, "fields": {"usuario": ["analista"], "username": "analista", "accion": "CREAR", "modelo": "TicketSoporte", "objeto_id": 5, "objeto_repr": "#5 - Otra Prueba", "detalle": "Asunto: Otra Prueba", "direccion_ip": "172.10.2.42", "fecha": "2026-06-04T21:01:40.087Z"}}, {"model": "direccion.auditlog", "pk": 49, "fields": {"usuario": ["admin"], "username": "admin", "accion": "EXPORTAR", "modelo": "Personal", "objeto_id": null, "objeto_repr": "Exportaci├│n PDF", "detalle": "2 registros", "direccion_ip": "172.10.2.43", "fecha": "2026-06-04T21:12:12.414Z"}}, {"model": "direccion.auditlog", "pk": 50, "fields": {"usuario": ["admin"], "username": "admin", "accion": "EXPORTAR", "modelo": "InformeDiario", "objeto_id": null, "objeto_repr": "PDF June 2026", "detalle": "0 informes", "direccion_ip": "172.10.2.42", "fecha": "2026-06-04T22:03:28.468Z"}}, {"model": "direccion.auditlog", "pk": 51, "fields": {"usuario": ["admin"], "username": "admin", "accion": "EXPORTAR", "modelo": "InformeDiario", "objeto_id": null, "objeto_repr": "ZIP informes_june_2026.zip", "detalle": "0 informe(s)", "direccion_ip": "192.168.0.104", "fecha": "2026-06-05T15:43:54.658Z"}}, {"model": "direccion.ticketsoporte", "pk": 1, "fields": {"asunto": "Test ticket", "descripcion": "Desc", "estado": "ABIERTO", "prioridad": "MEDIO", "creado_por": ["diag_admin2"], "asignado_a": null, "fecha_creacion": "2026-06-04T20:33:35.817Z", "fecha_actualizacion": "2026-06-04T20:57:01.379Z"}}, {"model": "direccion.ticketsoporte", "pk": 2, "fields": {"asunto": "Test ticket", "descripcion": "Desc", "estado": "RESUELTO", "prioridad": "MEDIO", "creado_por": ["diag_admin3"], "asignado_a": null, "fecha_creacion": "2026-06-04T20:34:00.940Z", "fecha_actualizacion": "2026-06-04T20:56:53.681Z"}}, {"model": "direccion.ticketsoporte", "pk": 3, "fields": {"asunto": "Test", "descripcion": "Desc", "estado": "RESUELTO", "prioridad": "MEDIO", "creado_por": ["diag_super"], "asignado_a": null, "fecha_creacion": "2026-06-04T20:34:17.540Z", "fecha_actualizacion": "2026-06-04T20:56:54.623Z"}}, {"model": "direccion.ticketsoporte", "pk": 4, "fields": {"asunto": "Prueba", "descripcion": "Pa probar los tickets", "estado": "ABIERTO", "prioridad": "BAJO", "creado_por": ["analista"], "asignado_a": null, "fecha_creacion": "2026-06-04T21:00:21.996Z", "fecha_actualizacion": "2026-06-04T21:00:21.996Z"}}, {"model": "direccion.ticketsoporte", "pk": 5, "fields": {"asunto": "Otra Prueba", "descripcion": "Para probar otra vez", "estado": "ABIERTO", "prioridad": "MEDIO", "creado_por": ["analista"], "asignado_a": null, "fecha_creacion": "2026-06-04T21:01:40.065Z", "fecha_actualizacion": "2026-06-04T21:01:40.065Z"}}, {"model": "direccion.tickethistorial", "pk": 1, "fields": {"ticket": 1, "usuario": ["admin"], "campo": "estado", "valor_anterior": "Abierto", "valor_nuevo": "Resuelto", "fecha": "2026-06-04T20:56:51.864Z"}}, {"model": "direccion.tickethistorial", "pk": 2, "fields": {"ticket": 2, "usuario": ["admin"], "campo": "estado", "valor_anterior": "Abierto", "valor_nuevo": "Resuelto", "fecha": "2026-06-04T20:56:53.686Z"}}, {"model": "direccion.tickethistorial", "pk": 3, "fields": {"ticket": 3, "usuario": ["admin"], "campo": "estado", "valor_anterior": "Abierto", "valor_nuevo": "Resuelto", "fecha": "2026-06-04T20:56:54.629Z"}}, {"model": "direccion.tickethistorial", "pk": 4, "fields": {"ticket": 1, "usuario": ["admin"], "campo": "estado", "valor_anterior": "Resuelto", "valor_nuevo": "Abierto", "fecha": "2026-06-04T20:57:01.386Z"}}, {"model": "direccion.tickethistorial", "pk": 5, "fields": {"ticket": 4, "usuario": ["analista"], "campo": "estado", "valor_anterior": "---", "valor_nuevo": "Abierto", "fecha": "2026-06-04T21:00:22.003Z"}}, {"model": "direccion.tickethistorial", "pk": 6, "fields": {"ticket": 4, "usuario": ["analista"], "campo": "prioridad", "valor_anterior": "---", "valor_nuevo": "Bajo", "fecha": "2026-06-04T21:00:22.014Z"}}, {"model": "direccion.tickethistorial", "pk": 7, "fields": {"ticket": 5, "usuario": ["analista"], "campo": "estado", "valor_anterior": "---", "valor_nuevo": "Abierto", "fecha": "2026-06-04T21:01:40.073Z"}}, {"model": "direccion.tickethistorial", "pk": 8, "fields": {"ticket": 5, "usuario": ["analista"], "campo": "prioridad", "valor_anterior": "---", "valor_nuevo": "Medio", "fecha": "2026-06-04T21:01:40.080Z"}}, {"model": "direccion.notificacion", "pk": 1, "fields": {"usuario": ["admin"], "mensaje": "Nuevo ticket #4: Prueba (por Carlos Analista)", "link": "/tickets/", "leida": true, "fecha_creacion": "2026-06-04T21:00:22.031Z"}}, {"model": "direccion.notificacion", "pk": 2, "fields": {"usuario": ["carlosmasacre"], "mensaje": "Nuevo ticket #4: Prueba (por Carlos Analista)", "link": "/tickets/", "leida": false, "fecha_creacion": "2026-06-04T21:00:22.031Z"}}, {"model": "direccion.notificacion", "pk": 3, "fields": {"usuario": ["tirsomota"], "mensaje": "Nuevo ticket #4: Prueba (por Carlos Analista)", "link": "/tickets/", "leida": false, "fecha_creacion": "2026-06-04T21:00:22.031Z"}}, {"model": "direccion.notificacion", "pk": 4, "fields": {"usuario": ["diag_admin"], "mensaje": "Nuevo ticket #4: Prueba (por Carlos Analista)", "link": "/tickets/", "leida": false, "fecha_creacion": "2026-06-04T21:00:22.031Z"}}, {"model": "direccion.notificacion", "pk": 5, "fields": {"usuario": ["diag_admin2"], "mensaje": "Nuevo ticket #4: Prueba (por Carlos Analista)", "link": "/tickets/", "leida": false, "fecha_creacion": "2026-06-04T21:00:22.031Z"}}, {"model": "direccion.notificacion", "pk": 6, "fields": {"usuario": ["diag_admin3"], "mensaje": "Nuevo ticket #4: Prueba (por Carlos Analista)", "link": "/tickets/", "leida": false, "fecha_creacion": "2026-06-04T21:00:22.031Z"}}, {"model": "direccion.notificacion", "pk": 7, "fields": {"usuario": ["diag_super"], "mensaje": "Nuevo ticket #4: Prueba (por Carlos Analista)", "link": "/tickets/", "leida": false, "fecha_creacion": "2026-06-04T21:00:22.031Z"}}, {"model": "direccion.notificacion", "pk": 8, "fields": {"usuario": ["admin"], "mensaje": "Nuevo ticket #5: Otra Prueba (por Carlos Analista)", "link": "/tickets/", "leida": true, "fecha_creacion": "2026-06-04T21:01:40.097Z"}}, {"model": "direccion.notificacion", "pk": 9, "fields": {"usuario": ["carlosmasacre"], "mensaje": "Nuevo ticket #5: Otra Prueba (por Carlos Analista)", "link": "/tickets/", "leida": false, "fecha_creacion": "2026-06-04T21:01:40.097Z"}}, {"model": "direccion.notificacion", "pk": 10, "fields": {"usuario": ["tirsomota"], "mensaje": "Nuevo ticket #5: Otra Prueba (por Carlos Analista)", "link": "/tickets/", "leida": false, "fecha_creacion": "2026-06-04T21:01:40.097Z"}}, {"model": "direccion.notificacion", "pk": 11, "fields": {"usuario": ["diag_admin"], "mensaje": "Nuevo ticket #5: Otra Prueba (por Carlos Analista)", "link": "/tickets/", "leida": false, "fecha_creacion": "2026-06-04T21:01:40.097Z"}}, {"model": "direccion.notificacion", "pk": 12, "fields": {"usuario": ["diag_admin2"], "mensaje": "Nuevo ticket #5: Otra Prueba (por Carlos Analista)", "link": "/tickets/", "leida": false, "fecha_creacion": "2026-06-04T21:01:40.097Z"}}, {"model": "direccion.notificacion", "pk": 13, "fields": {"usuario": ["diag_admin3"], "mensaje": "Nuevo ticket #5: Otra Prueba (por Carlos Analista)", "link": "/tickets/", "leida": false, "fecha_creacion": "2026-06-04T21:01:40.097Z"}}, {"model": "direccion.notificacion", "pk": 14, "fields": {"usuario": ["diag_super"], "mensaje": "Nuevo ticket #5: Otra Prueba (por Carlos Analista)", "link": "/tickets/", "leida": false, "fecha_creacion": "2026-06-04T21:01:40.097Z"}}, {"model": "direccion.documentoinvestigado", "pk": 1, "fields": {"investigado": 1, "archivo": "investigados/documentos/V-13338296/Perfil_Primario_Jos├®_Rubiano.pdf", "tipo": "PDF", "descripcion": null, "fecha_subida": "2026-06-04T20:56:02.686Z"}}]
